pywe_component_preauthcode/__init__.py
pywe_component_preauthcode/basepreauthcode.py
pywe_component_preauthcode/preauthcode.py
pywe_component_preauthcode-1.0.3.dist-info/DESCRIPTION.rst
pywe_component_preauthcode-1.0.3.dist-info/METADATA
pywe_component_preauthcode-1.0.3.dist-info/RECORD
pywe_component_preauthcode-1.0.3.dist-info/WHEEL
pywe_component_preauthcode-1.0.3.dist-info/metadata.json
pywe_component_preauthcode-1.0.3.dist-info/top_level.txt
