Metadata-Version: 2.0
Name: pywe-component-preauthcode
Version: 1.0.3
Summary: Wechat Component PreAuthCode Module for Python.
Home-page: https://github.com/sdkwe/pywe-component-preauthcode
Author: Hackathon
Author-email: kimi.huang@brightcells.com
License: UNKNOWN
Keywords: Wechat Weixin Component PreAuthCode
Platform: UNKNOWN
Classifier: License :: OSI Approved :: BSD License
Classifier: Programming Language :: Python
Classifier: Programming Language :: Python :: 2
Classifier: Programming Language :: Python :: 2.6
Classifier: Programming Language :: Python :: 2.7
Classifier: Programming Language :: Python :: 3
Classifier: Programming Language :: Python :: 3.2
Classifier: Programming Language :: Python :: 3.3
Classifier: Programming Language :: Python :: 3.4
Classifier: Programming Language :: Python :: 3.5
Classifier: Programming Language :: Python :: 3.6
Classifier: Topic :: Software Development :: Libraries :: Python Modules
Requires-Dist: pywe-base
Requires-Dist: pywe-component-token
Requires-Dist: pywe-exception
Requires-Dist: pywe-storage
